binance_db/__init__.py
binance_db/candle.py
binance_db/db.py
binance_db-0.0.1.dist-info/METADATA
binance_db-0.0.1.dist-info/RECORD
binance_db-0.0.1.dist-info/WHEEL
binance_db-0.0.1.dist-info/top_level.txt
