Metadata-Version: 2.1
Name: binance-db
Version: 0.0.1
Summary: Binance data cache
Home-page: https://github.com/StoicPerlman/binance-db
Author: Sam Kleiner
Author-email: sam@skleiner.com
License: UNKNOWN
Keywords: binance data cache
Platform: UNKNOWN
Classifier: Development Status :: 3 - Alpha
Classifier: Intended Audience :: Developers
Classifier: License :: OSI Approved :: MIT License
Classifier: Programming Language :: Python :: 3
Classifier: Programming Language :: Python :: 3.4
Classifier: Programming Language :: Python :: 3.5
Classifier: Programming Language :: Python :: 3.6
Requires-Dist: sqlalchemy
Requires-Dist: psycopg2-binary
Requires-Dist: python-binance
